{
  "services": [
    {
      "service_name": "Project Plan",
      "service_content": "Find comprehensive planning solutions tailored to specific project needs."
    },
    {
      "service_name": "Interior Work",
      "service_content": "Discover customized design concepts and implementation strategies for transforming spaces."
    },
    {
      "service_name": "Retail Design",
      "service_content": "Explore innovative and functional design solutions for enhancing retail environments and customer experiences."
    },
    {
      "service_name": "2D/3D Art Work",
      "service_content": "Experience artistic creations and visualizations that breathe life into ideas with precision and creativity."
    },
    {
      "service_name": "Interior Work",
      "service_content": "Access personalized design consultations and detailed plans for realizing space visions."
    },
    {
      "service_name": "Decoration Work",
      "service_content": "Discover unique and stylish decoration solutions reflecting personality and elevating spaces."
    }
  ]
}
